db_copilot/__init__.py
db_copilot-0.0.1.dist-info/METADATA
db_copilot-0.0.1.dist-info/WHEEL
db_copilot-0.0.1.dist-info/top_level.txt
db_copilot-0.0.1.dist-info/RECORD
