Metadata-Version: 2.1
Name: db-copilot
Version: 0.0.1
Summary: db-copilot
Author-email: Zeqi Lin <zeqi.lin@outlook.com>
Classifier: Programming Language :: Python :: 3
Classifier: License :: OSI Approved :: MIT License
Classifier: Operating System :: OS Independent
Requires-Python: >=3.8
